airflow_plugins/__init__.py
airflow_plugins/utils.py
airflow_plugins/xcom.py
airflow_plugins/hooks/__init__.py
airflow_plugins/hooks/ftp_hook.py
airflow_plugins/operators/__init__.py
airflow_plugins/operators/base.py
airflow_plugins/operators/cookiecutter.py
airflow_plugins/operators/csv.py
airflow_plugins/operators/db.py
airflow_plugins/operators/defer.py
airflow_plugins/operators/files.py
airflow_plugins/operators/git.py
airflow_plugins/operators/mixins.py
airflow_plugins/operators/run_evaluation.py
airflow_plugins/operators/zip.py
airflow_plugins/operators/sensors/__init__.py
airflow_plugins/operators/sensors/file_sensor.py
airflow_plugins/operators/sensors/task_sensor.py
airflow_plugins/operators/slack/__init__.py
airflow_plugins/operators/slack/hooks.py
airflow_plugins/operators/slack/notifications.py
airflow_plugins/operators/slack/operators.py
airflow_plugins/operators/slack/sensors.py
airflow_plugins/variables/__init__.py
airflow_plugins/variables/value_resolver.py
airflow_plugins-0.1.3.dist-info/DESCRIPTION.rst
airflow_plugins-0.1.3.dist-info/METADATA
airflow_plugins-0.1.3.dist-info/RECORD
airflow_plugins-0.1.3.dist-info/WHEEL
airflow_plugins-0.1.3.dist-info/metadata.json
airflow_plugins-0.1.3.dist-info/top_level.txt
